riskcube/__init__.py
riskcube/riskcube.py
riskcube/setup.py
riskcube-1.0.0.dist-info/LICENSE
riskcube-1.0.0.dist-info/METADATA
riskcube-1.0.0.dist-info/WHEEL
riskcube-1.0.0.dist-info/top_level.txt
riskcube-1.0.0.dist-info/RECORD
