Metadata-Version: 2.1
Name: riskcube
Version: 1.0.0
Summary: API Connector for riskcube
Home-page: https://gitlab.giordano.ch/python-packages/riskcube/
Author: giordano.ch ag
Author-email: info@giordano.ch
License: UNKNOWN
Project-URL: Bug Tracker, https://gitlab.giordano.ch/python-packages/riskcube/-/issues
Platform: UNKNOWN
Classifier: Programming Language :: Python :: 3
Classifier: License :: OSI Approved :: MIT License
Classifier: Operating System :: OS Independent
Requires-Python: >=3.6
License-File: LICENSE
